<?xml version="1.0" encoding="utf-8"?>
<aiscript name="lib.gt.cache.search" xmlns:xsi="http://www.w3.org/2001/XMLSchema-instance" xsi:noNamespaceSchemaLocation="../../stock_game/X4 Foundations/libraries/aiscripts.xsd" version="4">
  <params>
    <param name="cachePool" default="'mk3'" comment="Trade cache pool: mk3 (traders) or mk4 (supply)"/>
    <param name="ship" default="this.ship"/>
    <param name="searchMode" default="'buy_and_sell'"/>
    <param name="homeSector" default="this.ship.sector"/>
    <param name="maxDistance" default="0"/>
    <param name="wareBasket" default="[]"/>
    <param name="minROI" default="0"/>
    <param name="minAbsoluteProfit" default="0"/>
    <param name="ignoreBuildStorage" default="false"/>
    <param name="ignoreCarrierAux" default="false"/>
    <param name="maxEntries" default="100"/>
    <param name="cacheReadOffset" default="0" comment="Rotates cache scan start so concurrent fleet ships pick different entries first"/>
    <param name="cacheMaxAge" default="300s"/> <!-- Matches $Fleet.$CacheTTL default -->
    <param name="cacheDropoffTolerance" default="15"/> <!-- Max % profit drop from cached value before rejection; also % slack on average-price band width at read (0 = strict band) -->
    <param name="sellPriceMax" default="1.0" comment="Max vs ware average for supplier sell offers (ship buys). Normalized -1..+1 offset; 1.0 = no filter (isolated). Matches live search SellPriceMax."/>
    <param name="buyPriceMin" default="-1.0" comment="Min vs ware average for customer buy offers (ship sells). Normalized -1..+1 offset; -1.0 = no filter (isolated). Matches live search BuyPriceMin."/>
    <param name="bypassPlayerSellerPricing" default="false" comment="When true, skip supplier price-band purge for player-owned suppliers (MK3 Ignore Player Pricing)."/>
    <param name="minCargoUtilPercent" default="10"/> <!-- Hard minimum cargo utilization threshold (10-100) -->
    <param name="enableMinCargoUtil" default="true"/>
    <!-- MK4 compatibility params (accepted for call-site compatibility; current cache filter logic is generic) -->
    <param name="mk4AllowResources" default="true"/>
    <param name="mk4AllowIntermediates" default="true"/>
    <param name="mk4AllowTradewares" default="true"/>
    <param name="mk4DedicatedServe" default="false"/>
    <param name="mk4AnchorHome" default="null"/>
    <param name="mk4BuildStorageOnlyMode" default="false"/>
    <param name="maxDistanceBuy" default="0"/>
    <param name="maxDistanceSell" default="0"/>
    <param name="requirePlayerDeliveryStation" default="false"/>
    <param name="requirePlayerSupplierStation" default="false"/>
    <param name="requireNonPlayerSupplierStation" default="false"/>
    <!-- MK3 'Ignore Player Pricing' companion filter: when true, drop cache entries whose delivery (customer) station is player-owned. -->
    <param name="requireNonPlayerDeliveryStation" default="false"/>
    <param name="ignoreTradeRules" default="false" comment="When false, drop entries where a player-owned station's trade rules block the pair (NPC×NPC ignores cantradewith)."/>
    <param name="debugchance" default="0"/>
  </params>
  <patch sinceversion="3">
    <do_if value="not this.$gt_yieldMs?">
      <set_value name="this.$gt_yieldMs" exact="1"/>
    </do_if>
  </patch>
  <patch sinceversion="4">
    <do_if value="not $cachePool?">
      <set_value name="$cachePool" exact="'mk3'"/>
    </do_if>
  </patch>
  <attention min="unknown">
    <actions>
      <create_list name="$tradeList"/>
      <set_value name="$bestTrade" exact="null"/>
      <set_value name="$bestScore" exact="0"/>

      <!-- Read AI yield interval from global settings (persisted to instance var to survive waits) -->
      <set_value name="this.$gt_yieldMs" exact="1"/>
      <do_if value="global.$GT_GlobalSettings? and global.$GT_GlobalSettings.$Performance? and global.$GT_GlobalSettings.$Performance.$AIYieldInterval?">
        <set_value name="this.$gt_yieldMs" exact="[1, @global.$GT_GlobalSettings.$Performance.$AIYieldInterval].max"/>
      </do_if>

      <set_value name="this.$gt_cachePoolIsMk4" exact="$cachePool == 'mk4'"/>
      <set_value name="$cacheHomeKey" exact="$homeSector"/>
      <set_value name="$homeCache" exact="null"/>
      <do_if value="this.$gt_cachePoolIsMk4">
        <set_value name="$homeCache" exact="@global.$GT_TradeCacheMK4.{$homeSector}"/>
      </do_if>
      <do_else>
        <set_value name="$homeCache" exact="@global.$GT_TradeCache.{$homeSector}"/>
      </do_else>
      <set_value name="$homeCacheCount" exact="0"/>
      <do_if value="$homeCache?">
        <set_value name="$homeCacheCount" exact="@$homeCache.count"/>
      </do_if>
      <!-- Sector table-key reconciliation: lookup can miss when homeSector ref differs from writer key. -->
      <do_if value="$homeCacheCount == 0 and this.$gt_cachePoolIsMk4 and global.$GT_TradeCacheMK4? and $homeSector? and $homeSector.exists">
        <set_value name="$mk4CacheKeys" exact="@global.$GT_TradeCacheMK4.keys"/>
        <set_value name="$mk4CacheKeyCount" exact="0"/>
        <do_if value="$mk4CacheKeys?">
          <set_value name="$mk4CacheKeyCount" exact="@$mk4CacheKeys.count"/>
        </do_if>
        <do_if value="$mk4CacheKeyCount gt 0">
          <do_all exact="$mk4CacheKeyCount" counter="$cki">
            <set_value name="$ckiSector" exact="@$mk4CacheKeys.{$cki}"/>
            <do_if value="$ckiSector? and $ckiSector.exists and $ckiSector == $homeSector">
              <set_value name="$cacheHomeKey" exact="$ckiSector"/>
              <set_value name="$homeCache" exact="@global.$GT_TradeCacheMK4.{$ckiSector}"/>
              <break/>
            </do_if>
          </do_all>
        </do_if>
        <do_if value="$homeCache?">
          <set_value name="$homeCacheCount" exact="@$homeCache.count"/>
        </do_if>
      </do_if>
      <set_value name="$purgedStaleCount" exact="0"/>
      <do_if value="$homeCacheCount == 0">
        <return value="table[
          $Found = false,
          $BestTrade = null,
          $BestScore = 0,
          $TradeList = $tradeList,
          $PurgedStale = 0,
          $PoolSizeAfter = 0
        ]"/>
      </do_if>

      <set_value name="this.$cleanupBatchSize" exact="50"/>
      <do_if value="global.$GT_GlobalSettings? and global.$GT_GlobalSettings.$Performance? and global.$GT_GlobalSettings.$Performance.$CacheCleanupBatchSize?">
        <set_value name="this.$cleanupBatchSize" exact="[10, @global.$GT_GlobalSettings.$Performance.$CacheCleanupBatchSize].max"/>
      </do_if>
      <set_value name="this.$cleanupBatchSize" exact="(this.$cleanupBatchSize)i"/>
      <set_value name="$now" exact="player.age"/>
      <!-- Average-price band thresholds (quantityfactor = unitprice / ware.averageprice).
           Matches slider intent (-20% buy / +20% sell vs galaxy average), not station-local relativeprice. -->
      <set_value name="$bandSellMax" exact="if $sellPriceMax? then $sellPriceMax else 1.0"/>
      <set_value name="$bandBuyMin" exact="if $buyPriceMin? then $buyPriceMin else -1.0"/>
      <set_value name="$bandPriceCheckActive" exact="false"/>
      <set_value name="$bandSellMaxRelaxed" exact="$bandSellMax"/>
      <set_value name="$bandBuyMinRelaxed" exact="$bandBuyMin"/>
      <set_value name="$bandSupplierQtyMax" exact="2.0"/>
      <set_value name="$bandCustomerQtyMin" exact="0.0"/>
      <set_value name="$bandMinQtySpread" exact="0.0"/>
      <do_if value="not ($bandSellMax ge 1.0 and $bandBuyMin le -1.0)">
        <set_value name="$bandPriceCheckActive" exact="true"/>
        <set_value name="$bandDropoffPct" exact="if $cacheDropoffTolerance? and $cacheDropoffTolerance gt 0 then $cacheDropoffTolerance else 0"/>
        <set_value name="$bandSellSlack" exact="[$bandSellMax, -$bandSellMax].max * ($bandDropoffPct / 100.0)"/>
        <set_value name="$bandBuySlack" exact="[$bandBuyMin, -$bandBuyMin].max * ($bandDropoffPct / 100.0)"/>
        <set_value name="$bandSellMaxRelaxed" exact="$bandSellMax + $bandSellSlack"/>
        <set_value name="$bandBuyMinRelaxed" exact="$bandBuyMin - $bandBuySlack"/>
        <set_value name="$bandSupplierQtyMax" exact="1.0 + $bandSellMaxRelaxed"/>
        <set_value name="$bandCustomerQtyMin" exact="1.0 + $bandBuyMinRelaxed"/>
        <set_value name="$bandMinQtySpread" exact="$bandBuyMinRelaxed - $bandSellMaxRelaxed"/>
      </do_if>
      <!-- Read-time purge: TTL + dead refs only. Average-price band is per-ship at read (lib.gt.cache.search). -->
      <do_all exact="$homeCacheCount" counter="$pci" reverse="true">
        <set_value name="$livePurgeCount" exact="0"/>
        <do_if value="this.$gt_cachePoolIsMk4">
          <set_value name="$livePurgeCount" exact="if @global.$GT_TradeCacheMK4.{$cacheHomeKey}.count != null then @global.$GT_TradeCacheMK4.{$cacheHomeKey}.count else 0"/>
        </do_if>
        <do_else>
          <set_value name="$livePurgeCount" exact="if @global.$GT_TradeCache.{$cacheHomeKey}.count != null then @global.$GT_TradeCache.{$cacheHomeKey}.count else 0"/>
        </do_else>
        <do_if value="$pci gt $livePurgeCount">
          <continue/>
        </do_if>
        <set_value name="$purgeEntry" exact="null"/>
        <do_if value="this.$gt_cachePoolIsMk4">
          <set_value name="$purgeEntry" exact="@global.$GT_TradeCacheMK4.{$cacheHomeKey}.{$pci}"/>
        </do_if>
        <do_else>
          <set_value name="$purgeEntry" exact="@global.$GT_TradeCache.{$cacheHomeKey}.{$pci}"/>
        </do_else>
        <set_value name="$purgeRemove" exact="false"/>
        <do_if value="not $purgeEntry?">
          <set_value name="$purgeRemove" exact="true"/>
        </do_if>
        <do_if value="not $purgeRemove and (not $purgeEntry.$Score? or $purgeEntry.$Score le 0)">
          <set_value name="$purgeRemove" exact="true"/>
        </do_if>
        <set_value name="$purgeTs" exact="null"/>
        <do_if value="not $purgeRemove">
          <set_value name="$purgeTs" exact="@$purgeEntry.$CachedAt"/>
          <do_if value="$purgeTs == null">
            <set_value name="$purgeTs" exact="@$purgeEntry.$Timestamp"/>
          </do_if>
          <do_if value="$purgeTs != null and ($now - $purgeTs) gt $cacheMaxAge">
            <set_value name="$purgeRemove" exact="true"/>
          </do_if>
        </do_if>
        <do_if value="not $purgeRemove and @$purgeEntry.$BuyOffer != null and not @$purgeEntry.$BuyOffer.exists">
          <set_value name="$purgeRemove" exact="true"/>
        </do_if>
        <!-- Customer buy-offer refs refresh continuously; rows with permanent keys are re-discovered at read. -->
        <set_value name="$purgeReResolvable" exact="@$purgeEntry.$SellSector != null and @$purgeEntry.$SellSector.exists and (@$purgeEntry.$Ware != null or @$purgeEntry.$DeliveryStationName != null) and (@$purgeEntry.$DeliveryStationId != null or @$purgeEntry.$DeliveryStationName != null)"/>
        <do_if value="not $purgeRemove and not $purgeReResolvable and @$purgeEntry.$SellOffer != null and not @$purgeEntry.$SellOffer.exists">
          <set_value name="$purgeRemove" exact="true"/>
        </do_if>
        <do_if value="not $purgeRemove and not $purgeReResolvable and @$purgeEntry.$SellStation != null and not @$purgeEntry.$SellStation.exists">
          <set_value name="$purgeRemove" exact="true"/>
        </do_if>
        <!-- Universal station resolution: drop rows no ship can use (dead delivery/supplier refs). -->
        <do_if value="not $purgeRemove and not $purgeReResolvable">
          <set_value name="$purgeSellStation" exact="null"/>
          <do_if value="$purgeEntry.$SellOffer? and @$purgeEntry.$SellOffer.exists and $purgeEntry.$SellOffer.buyer? and @$purgeEntry.$SellOffer.buyer.exists">
            <set_value name="$purgeSellStation" exact="@$purgeEntry.$SellOffer.buyer"/>
          </do_if>
          <do_if value="not $purgeSellStation? and $purgeEntry.$SellStation? and @$purgeEntry.$SellStation.exists">
            <set_value name="$purgeSellStation" exact="$purgeEntry.$SellStation"/>
          </do_if>
          <do_if value="not $purgeSellStation? and $purgeEntry.$SellOffer? and @$purgeEntry.$SellOffer.exists and $purgeEntry.$SellOffer.owner? and @$purgeEntry.$SellOffer.owner.exists">
            <set_value name="$purgeSellStation" exact="@$purgeEntry.$SellOffer.owner"/>
          </do_if>
          <do_if value="not $purgeSellStation? or not @$purgeSellStation.exists">
            <set_value name="$purgeRemove" exact="true"/>
          </do_if>
          <do_if value="not $purgeRemove and not ($purgeEntry.$IsSellOnly? and $purgeEntry.$IsSellOnly)">
            <set_value name="$purgeBuyStation" exact="null"/>
            <do_if value="$purgeEntry.$BuyStation? and @$purgeEntry.$BuyStation.exists">
              <set_value name="$purgeBuyStation" exact="$purgeEntry.$BuyStation"/>
            </do_if>
            <do_if value="not $purgeBuyStation? and $purgeEntry.$BuyOffer? and @$purgeEntry.$BuyOffer.exists">
              <do_if value="$purgeEntry.$BuyOffer.seller? and @$purgeEntry.$BuyOffer.seller.exists">
                <set_value name="$purgeBuyStation" exact="@$purgeEntry.$BuyOffer.seller"/>
              </do_if>
              <do_elseif value="$purgeEntry.$BuyOffer.owner? and @$purgeEntry.$BuyOffer.owner.exists">
                <set_value name="$purgeBuyStation" exact="@$purgeEntry.$BuyOffer.owner"/>
              </do_elseif>
            </do_if>
            <do_if value="not $purgeBuyStation? or not @$purgeBuyStation.exists">
              <set_value name="$purgeRemove" exact="true"/>
            </do_if>
          </do_if>
        </do_if>
        <do_if value="$purgeRemove">
          <set_value name="$liveBeforeRemove" exact="0"/>
          <do_if value="this.$gt_cachePoolIsMk4">
            <set_value name="$liveBeforeRemove" exact="if @global.$GT_TradeCacheMK4.{$cacheHomeKey}.count != null then @global.$GT_TradeCacheMK4.{$cacheHomeKey}.count else 0"/>
          </do_if>
          <do_else>
            <set_value name="$liveBeforeRemove" exact="if @global.$GT_TradeCache.{$cacheHomeKey}.count != null then @global.$GT_TradeCache.{$cacheHomeKey}.count else 0"/>
          </do_else>
          <do_if value="$pci le $liveBeforeRemove">
            <do_if value="this.$gt_cachePoolIsMk4">
              <remove_value name="global.$GT_TradeCacheMK4.{$cacheHomeKey}.{$pci}"/>
            </do_if>
            <do_else>
              <remove_value name="global.$GT_TradeCache.{$cacheHomeKey}.{$pci}"/>
            </do_else>
            <set_value name="$purgedStaleCount" operation="add"/>
          </do_if>
        </do_if>
        <set_value name="$pciInt" exact="($pci)i"/>
        <do_if value="($pciInt % this.$cleanupBatchSize) == 0">
          <wait exact="this.$gt_yieldMs * 1ms" comment="Yield read-time purge loop"/>
        </do_if>
      </do_all>
      <do_if value="$purgedStaleCount gt 0">
        <set_value name="$homeCache" exact="null"/>
        <do_if value="this.$gt_cachePoolIsMk4">
          <set_value name="$homeCache" exact="@global.$GT_TradeCacheMK4.{$cacheHomeKey}"/>
        </do_if>
        <do_else>
          <set_value name="$homeCache" exact="@global.$GT_TradeCache.{$cacheHomeKey}"/>
        </do_else>
        <set_value name="$homeCacheCount" exact="0"/>
        <do_if value="$homeCache?">
          <set_value name="$homeCacheCount" exact="@$homeCache.count"/>
        </do_if>
        <set_value name="$poolLabel" exact="if this.$gt_cachePoolIsMk4 then 'MK4' else 'MK3'"/>
        <do_if value="@global.$GT_GlobalSettings.$Debug.$EnableDebugLogging">
          <debug_text text="'[GT-CacheSearch] ' + $ship.idcode + ': (' + $poolLabel + ') Read-time purge removed ' + $purgedStaleCount + ' stale entries from ' + $cacheHomeKey.knownname + ' (remaining: ' + $homeCacheCount + ')'" chance="100"/>
        </do_if>
      </do_if>
      <do_if value="$homeCacheCount == 0">
        <return value="table[
          $Found = false,
          $BestTrade = null,
          $BestScore = 0,
          $TradeList = $tradeList,
          $PurgedStale = $purgedStaleCount,
          $PoolSizeAfter = 0
        ]"/>
      </do_if>

      <set_value name="$maxDistanceBuyLeg" exact="if $maxDistanceBuy? and $maxDistanceBuy gt 0 then $maxDistanceBuy else $maxDistance"/>
      <set_value name="$maxDistanceSellLeg" exact="if $maxDistanceSell? and $maxDistanceSell gt 0 then $maxDistanceSell else $maxDistance"/>
      <!-- If cache was populated with a smaller search radius than this ship needs, treat as miss
           so live search (with completion pass) can find trades outside the cached radius. -->
      <set_value name="$foundCount" exact="0"/>
      <set_value name="$isSellOnlySearch" exact="$searchMode == 'sell_only'"/>
      <set_value name="$wareBasketCount" exact="if $wareBasket? and typeof $wareBasket == datatype.list then $wareBasket.count else 0"/>
      <set_value name="$isIsolatedMode" exact="global.$GT_IsolatedTradeActive? and global.$GT_IsolatedTradeActive.{$ship}?"/>
      <set_value name="$cargoUtilThresholdPct" exact="[10,[$minCargoUtilPercent,100].min].max"/>
      <!-- Per-ware diversification: each ware gets a slice of the result window so low-score
           wares (e.g. small remainder deliveries) are not crowded out by a few dominant wares. -->
      <set_value name="$foundPerWare" exact="table[]"/>
      <!-- Memoize delivery re-discovery within this cache read (same station+ware appears in many entries). -->
      <set_value name="$deliveryResolveMemo" exact="table[]"/>
      <set_value name="$maxTradesPerWareSetting" exact="20"/>
      <do_if value="global.$GT_GlobalSettings? and global.$GT_GlobalSettings.$Performance? and global.$GT_GlobalSettings.$Performance.$MaxTradesPerWare?">
        <set_value name="$maxTradesPerWareSetting" exact="@global.$GT_GlobalSettings.$Performance.$MaxTradesPerWare"/>
      </do_if>
      <do_if value="$maxTradesPerWareSetting lt 1">
        <set_value name="$maxTradesPerWareSetting" exact="1"/>
      </do_if>
      <set_value name="$perWareCap" exact="$maxTradesPerWareSetting"/>
      <do_if value="$wareBasketCount gt 0">
        <set_value name="$perWareCapFromBudget" exact="[1, ($maxEntries / $wareBasketCount)i].max"/>
        <set_value name="$perWareCap" exact="[$perWareCapFromBudget, $maxTradesPerWareSetting].min"/>
      </do_if>
      <do_else>
        <set_value name="$perWareCap" exact="[2, [$maxTradesPerWareSetting, 5].min].max"/>
      </do_else>
      <!-- Iterate cache with per-ship rotation (cache is sorted by Score descending via lib.gt.cache.write).
           Without rotation, a fleet burst reads the same top entries and collides on fleet reservations.
           Collect up to $perWareCap valid trades per ware until $maxEntries total OR cache exhausted. -->
      <!-- NOTE: $homeCacheCount is a snapshot; the list can shrink mid-loop (MD purge/cleanup
           runs while this AI script yields). Guard with bounds check before access. -->
      <set_value name="$loopSpan" exact="[$homeCacheCount, 1].max"/>
      <set_value name="$startOffset" exact="0"/>
      <do_if value="$cacheReadOffset? and $loopSpan gt 0">
        <set_value name="$startOffset" exact="(($cacheReadOffset) % $loopSpan)"/>
      </do_if>
      <do_all exact="$loopSpan" counter="$visitIdx">
        <set_value name="$i" exact="(($startOffset + $visitIdx - 1) % $loopSpan) + 1"/>
        <!-- Bounds guard: list may have shrunk since $homeCacheCount was captured -->
        <do_if value="$i gt $homeCache.count">
          <continue/>
        </do_if>
        <set_value name="$entry" exact="@$homeCache.{$i}"/>
        <!-- Initialize per-entry offer capacities to avoid undefined-variable lookups -->
        <set_value name="$preCheckBuyAmt" exact="0"/>
        <set_value name="$preCheckSellAmt" exact="0"/>
        <!-- Resolve supplier/delivery stations: cached component refs go stale (0x0L) when
             stations are destroyed; prefer live offer seller/buyer when the stored ref is dead. -->
        <set_value name="$entryBuyStation" exact="null"/>
        <do_if value="$entry.$BuyStation? and @$entry.$BuyStation.exists">
          <set_value name="$entryBuyStation" exact="$entry.$BuyStation"/>
        </do_if>
        <do_if value="not $entryBuyStation? and $entry.$BuyOffer? and @$entry.$BuyOffer.exists">
          <do_if value="$entry.$BuyOffer.seller? and @$entry.$BuyOffer.seller.exists">
            <set_value name="$entryBuyStation" exact="@$entry.$BuyOffer.seller"/>
          </do_if>
          <do_elseif value="$entry.$BuyOffer.owner? and @$entry.$BuyOffer.owner.exists">
            <set_value name="$entryBuyStation" exact="@$entry.$BuyOffer.owner"/>
          </do_elseif>
        </do_if>
        <set_value name="$entrySellStationFromBuyer" exact="null"/>
        <do_if value="$entry.$SellOffer? and @$entry.$SellOffer.exists and $entry.$SellOffer.buyer? and @$entry.$SellOffer.buyer.exists">
          <set_value name="$entrySellStationFromBuyer" exact="@$entry.$SellOffer.buyer"/>
        </do_if>
        <set_value name="$entrySellStation" exact="null"/>
        <!-- Primary: stored delivery station, UNGUARDED (mirrors buy-station resolution above).
             CRITICAL: use '$x == null' value-tests below, NOT 'not $x?'. After
             <set_value exact="null"/> the variable is DEFINED, so '$x?' returns true and
             'not $x?' is always false - which previously skipped every resolver and left
             $entrySellStation a defined-null, rejecting 100% of cache entries (f68ba09 regression). -->
        <do_if value="$entry.$SellStation? and @$entry.$SellStation.exists">
          <set_value name="$entrySellStation" exact="$entry.$SellStation"/>
        </do_if>
        <do_if value="$entrySellStation == null and $entrySellStationFromBuyer? and @$entrySellStationFromBuyer.exists">
          <set_value name="$entrySellStation" exact="$entrySellStationFromBuyer"/>
        </do_if>
        <do_if value="$entrySellStation == null and $entry.$SellOffer? and @$entry.$SellOffer.exists and $entry.$SellOffer.owner? and @$entry.$SellOffer.owner.exists">
          <set_value name="$entrySellStation" exact="@$entry.$SellOffer.owner"/>
        </do_if>
        <!-- Prefer buildstorage buyer when the stored SellStation is the parent station (not the BS). -->
        <do_if value="$entrySellStation != null and @$entrySellStation.exists and not @$entrySellStation.isclass.buildstorage and $entrySellStationFromBuyer? and @$entrySellStationFromBuyer.exists and @$entrySellStationFromBuyer.isclass.buildstorage">
          <set_value name="$entrySellStation" exact="$entrySellStationFromBuyer"/>
        </do_if>
        <!-- MK4 build-storage-only mode: delivery buy-offer buyer is authoritative (overrides parent-HQ SellStation). -->
        <do_if value="$mk4BuildStorageOnlyMode and $entrySellStationFromBuyer? and @$entrySellStationFromBuyer.exists">
          <set_value name="$entrySellStation" exact="$entrySellStationFromBuyer"/>
        </do_if>
        <!-- Customer buy-offer / delivery-station refs die when offers refresh; re-discover from permanent keys (memoized, targeted queries). -->
        <do_if value="$entrySellStation == null or not @$entrySellStation.exists">
          <do_if value="$entry.$SellStationBase? and @$entry.$SellStationBase.exists">
            <set_value name="$entryBaseBuildStorage" exact="@$entry.$SellStationBase.buildstorage"/>
            <do_if value="$entryBaseBuildStorage? and @$entryBaseBuildStorage.exists">
              <set_value name="$entrySellStation" exact="$entryBaseBuildStorage"/>
              <set_value name="$entry.$SellStation" exact="$entryBaseBuildStorage"/>
            </do_if>
          </do_if>
          <set_value name="$reResolveWare" exact="if $entry.$Ware? then $entry.$Ware else null"/>
          <do_if value="$reResolveWare == null and $entry.$BuyOffer? and @$entry.$BuyOffer.exists and @$entry.$BuyOffer.ware != null">
            <set_value name="$reResolveWare" exact="@$entry.$BuyOffer.ware"/>
          </do_if>
          <do_if value="$reResolveWare == null and $entry.$SellOffer? and @$entry.$SellOffer.exists and @$entry.$SellOffer.ware != null">
            <set_value name="$reResolveWare" exact="@$entry.$SellOffer.ware"/>
          </do_if>
          <do_if value="($entrySellStation == null or not @$entrySellStation.exists) and $entry.$SellSector? and @$entry.$SellSector.exists and $reResolveWare?">
            <set_value name="$reMemoAnchor" exact="if $entry.$DeliveryStationId? then $entry.$DeliveryStationId else (if $entry.$DeliveryStationName? then $entry.$DeliveryStationName else null)"/>
            <set_value name="$reMemoKey" exact="null"/>
            <do_if value="$reMemoAnchor? and $reResolveWare? and $reResolveWare.name?">
              <set_value name="$reMemoKey" exact="$reMemoAnchor + '|' + @$reResolveWare.name"/>
            </do_if>
            <set_value name="$reMemoHit" exact="false"/>
            <do_if value="$reMemoKey? and $deliveryResolveMemo.{$reMemoKey}?">
              <set_value name="$reMemoHit" exact="true"/>
              <set_value name="$reMemoEntry" exact="$deliveryResolveMemo.{$reMemoKey}"/>
              <do_if value="$reMemoEntry.$Resolved? and $reMemoEntry.$Resolved and $reMemoEntry.$Station? and @$reMemoEntry.$Station.exists">
                <set_value name="$entrySellStation" exact="$reMemoEntry.$Station"/>
                <set_value name="$entry.$SellStation" exact="$reMemoEntry.$Station"/>
                <do_if value="$reMemoEntry.$Offer? and @$reMemoEntry.$Offer.exists">
                  <set_value name="$entry.$SellOffer" exact="$reMemoEntry.$Offer"/>
                </do_if>
              </do_if>
            </do_if>
            <do_if value="not $reMemoHit">
              <set_value name="$reTargetStation" exact="null"/>
              <set_value name="$reTargetOffer" exact="null"/>
              <do_if value="$entry.$DeliveryStationId?">
                <find_station name="$reStations" space="$entry.$SellSector" multiple="true"/>
                <do_if value="$reStations? and $reStations.count gt 0">
                  <do_for_each name="$reSt" in="$reStations">
                    <do_if value="not $reTargetStation? and $reSt? and @$reSt.exists and @$reSt.idcode == $entry.$DeliveryStationId">
                      <set_value name="$reTargetStation" exact="$reSt"/>
                    </do_if>
                  </do_for_each>
                </do_if>
                <do_if value="not $reTargetStation?">
                  <find_object name="$reBsObjs" class="class.buildstorage" space="$entry.$SellSector" owner="faction.player" multiple="true"/>
                  <do_if value="$reBsObjs? and $reBsObjs.count gt 0">
                    <do_for_each name="$reBsCand" in="$reBsObjs">
                      <do_if value="not $reTargetStation? and $reBsCand? and @$reBsCand.exists and $reBsCand.base? and @$reBsCand.base.exists and @$reBsCand.base.idcode == $entry.$DeliveryStationId">
                        <set_value name="$reTargetStation" exact="$reBsCand"/>
                      </do_if>
                    </do_for_each>
                  </do_if>
                </do_if>
              </do_if>
              <do_elseif value="$entry.$DeliveryStationName?">
                <find_station name="$reNameStations" space="$entry.$SellSector" multiple="true"/>
                <do_if value="$reNameStations? and $reNameStations.count gt 0">
                  <do_for_each name="$reNameSt" in="$reNameStations">
                    <do_if value="not $reTargetStation? and $reNameSt? and @$reNameSt.exists and $reNameSt.knownname? and @$reNameSt.knownname == $entry.$DeliveryStationName">
                      <set_value name="$reTargetStation" exact="$reNameSt"/>
                    </do_if>
                  </do_for_each>
                </do_if>
              </do_elseif>
              <do_if value="$reTargetStation? and @$reTargetStation.exists">
                <find_buy_offer buyer="$reTargetStation" tradepartner="$ship" wares="$reResolveWare" result="$reTargetOffers" multiple="true">
                  <offeramount min="1" tradepartner="$ship"/>
                </find_buy_offer>
                <do_if value="not ($reTargetOffers? and $reTargetOffers.count gt 0) and @$reTargetStation.isclass.buildstorage">
                  <find_buy_offer buyer="$reTargetStation" tradepartner="$ship" wares="$reResolveWare" result="$reTargetOffers" multiple="true" excludeempty="false" usereservations="false">
                    <offeramount min="1"/>
                  </find_buy_offer>
                </do_if>
                <do_if value="$reTargetOffers? and $reTargetOffers.count gt 0">
                  <set_value name="$reTargetOffer" exact="$reTargetOffers.{1}"/>
                </do_if>
              </do_if>
              <do_if value="$reMemoKey?">
                <set_value name="$deliveryResolveMemo.{$reMemoKey}" exact="table[
                  $Resolved = $reTargetStation? and @$reTargetStation.exists,
                  $Station = $reTargetStation,
                  $Offer = $reTargetOffer
                ]"/>
              </do_if>
              <do_if value="$reTargetStation? and @$reTargetStation.exists">
                <set_value name="$entrySellStation" exact="$reTargetStation"/>
                <set_value name="$entry.$SellStation" exact="$reTargetStation"/>
                <do_if value="$reTargetOffer? and @$reTargetOffer.exists">
                  <set_value name="$entry.$SellOffer" exact="$reTargetOffer"/>
                </do_if>
                <do_if value="not $entry.$DeliveryStationId?">
                  <do_if value="@$reTargetStation.isclass.buildstorage and $reTargetStation.base? and @$reTargetStation.base.exists">
                    <set_value name="$entry.$DeliveryStationId" exact="@$reTargetStation.base.idcode"/>
                    <set_value name="$entry.$SellStationBase" exact="@$reTargetStation.base"/>
                  </do_if>
                  <do_else>
                    <set_value name="$entry.$DeliveryStationId" exact="@$reTargetStation.idcode"/>
                  </do_else>
                </do_if>
              </do_if>
            </do_if>
          </do_if>
        </do_if>

        <!-- Basic validity -->
        <do_if value="not $entry? or not $entry.$Score? or $entry.$Score le 0">
          <continue/>
        </do_if>

        <!-- Ship-scoped cache failure: skip entries this ship already rejected (S1b). -->
        <do_if value="$entry.$FailedShips? and $entry.$FailedShips.count gt 0">
          <set_value name="$shipFailedOnEntry" exact="false"/>
          <do_all exact="$entry.$FailedShips.count" counter="$fsi">
            <do_if value="$entry.$FailedShips.{$fsi} == $ship">
              <set_value name="$shipFailedOnEntry" exact="true"/>
              <break/>
            </do_if>
          </do_all>
          <do_if value="$shipFailedOnEntry">
            <continue/>
          </do_if>
        </do_if>

        <!-- Search-mode guard:
             - sell_only: only sell-only entries for wares this ship is currently carrying
             - buy_and_sell: never pick sell-only disposal entries -->
        <do_if value="$isSellOnlySearch">
          <do_if value="not $entry.$IsSellOnly? or not $entry.$IsSellOnly">
            <continue/>
          </do_if>
          <do_if value="not $entry.$Ware? or $ship.cargo.{$entry.$Ware}.count le 0">
            <continue/>
          </do_if>
        </do_if>
        <do_else>
          <do_if value="$entry.$IsSellOnly? and $entry.$IsSellOnly">
            <continue/>
          </do_if>
        </do_else>

        <!-- Cargo bay compatibility: shared MK4 pool may contain trades from solid/liquid ships;
             skip wares this ship cannot carry (mirrors trade_found + GT_FilterTrade).
             $CargoWareTransport on MK4 entries survives stale ware refs. -->
        <do_if value="not $isSellOnlySearch">
          <set_value name="$cargoCompatWare" exact="if $entry.$Ware? then $entry.$Ware else null"/>
          <do_if value="$cargoCompatWare == null and $entry.$BuyOffer? and @$entry.$BuyOffer.exists and @$entry.$BuyOffer.ware != null">
            <set_value name="$cargoCompatWare" exact="@$entry.$BuyOffer.ware"/>
          </do_if>
          <do_if value="$cargoCompatWare == null and $entry.$SellOffer? and @$entry.$SellOffer.exists and @$entry.$SellOffer.ware != null">
            <set_value name="$cargoCompatWare" exact="@$entry.$SellOffer.ware"/>
          </do_if>
          <set_value name="$entryCargoTransport" exact="null"/>
          <do_if value="$entry.$CargoWareTransport?">
            <set_value name="$entryCargoTransport" exact="@$entry.$CargoWareTransport"/>
          </do_if>
          <do_elseif value="$cargoCompatWare?">
            <set_value name="$entryCargoTransport" exact="@$cargoCompatWare.waretransport"/>
          </do_elseif>
          <set_value name="$cargoHoldOk" exact="false"/>
          <do_if value="$cargoCompatWare? and @$ship.cargo.{$cargoCompatWare}.max gt 0">
            <set_value name="$cargoHoldOk" exact="true"/>
          </do_if>
          <do_elseif value="$entryCargoTransport? and $ship.waretransport.indexof.{$entryCargoTransport}">
            <set_value name="$cargoHoldOk" exact="true"/>
          </do_elseif>
          <do_if value="not $cargoHoldOk">
            <continue/>
          </do_if>
        </do_if>

        <!-- Ware basket filter (applies to all cache search modes when basket is non-empty). -->
        <do_if value="$wareBasketCount gt 0">
          <set_value name="$entryWare" exact="if $entry.$Ware? then $entry.$Ware else null"/>
          <do_if value="$entryWare == null and $entry.$BuyOffer? and @$entry.$BuyOffer.exists and @$entry.$BuyOffer.ware != null">
            <set_value name="$entryWare" exact="@$entry.$BuyOffer.ware"/>
          </do_if>
          <do_if value="$entryWare == null and $entry.$SellOffer? and @$entry.$SellOffer.exists and @$entry.$SellOffer.ware != null">
            <set_value name="$entryWare" exact="@$entry.$SellOffer.ware"/>
          </do_if>
          <set_value name="$wareAllowed" exact="false"/>
          <do_all exact="$wareBasketCount" counter="$wbIdx">
            <do_if value="$wareBasket.{$wbIdx} == $entryWare">
              <set_value name="$wareAllowed" exact="true"/>
              <break/>
            </do_if>
          </do_all>
          <do_if value="not $wareAllowed">
            <continue/>
          </do_if>
        </do_if>

        <!-- TTL / age check -->
        <do_if value="$entry.$CachedAt? and ($now - $entry.$CachedAt) gt $cacheMaxAge">
          <continue/>
        </do_if>

        <!-- Station existence (before distance / MK4 ware-type property access on station). -->
        <do_if value="not $entry.$IsSellOnly?">
          <do_if value="not $entryBuyStation? or not @$entryBuyStation.exists">
            <continue/>
          </do_if>
        </do_if>
        <do_if value="not $entrySellStation? or not @$entrySellStation.exists">
          <continue/>
        </do_if>

        <!-- MK4 policy filters (no-op for callers that don't pass these flags). -->
        <do_if value="not $entry.$IsSellOnly?">
          <do_if value="$requirePlayerDeliveryStation">
            <set_value name="$mk4DeliveryPlayerOk" exact="false"/>
            <do_if value="$entrySellStation? and @$entrySellStation.exists and @$entrySellStation.isplayerowned">
              <set_value name="$mk4DeliveryPlayerOk" exact="true"/>
            </do_if>
            <do_elseif value="$entrySellStation? and $entrySellStation.isclass.buildstorage and $entrySellStation.base? and @$entrySellStation.base.isplayerowned">
              <set_value name="$mk4DeliveryPlayerOk" exact="true"/>
            </do_elseif>
            <do_if value="not $mk4DeliveryPlayerOk">
              <continue/>
            </do_if>
          </do_if>
          <do_if value="$requirePlayerSupplierStation and (not $entryBuyStation? or not @$entryBuyStation.isplayerowned)">
            <continue/>
          </do_if>
          <do_if value="$requireNonPlayerSupplierStation and (not $entryBuyStation? or @$entryBuyStation.isplayerowned)">
            <continue/>
          </do_if>
        </do_if>
        <!-- 'Ignore Player Pricing' companion filter: drop any entry (including sell-only disposal)
             whose delivery destination is a player-owned station. -->
        <do_if value="$requireNonPlayerDeliveryStation and $entrySellStation? and @$entrySellStation.isplayerowned">
          <continue/>
        </do_if>
        <!-- MK4 serveHomeOnly: delivery must match home anchor (station + build storage, or sector). -->
        <do_if value="$mk4DedicatedServe and not $mk4BuildStorageOnlyMode">
          <set_value name="$serveHomeAnchor" exact="if $mk4AnchorHome? and $mk4AnchorHome.exists then $mk4AnchorHome else $homeSector"/>
          <set_value name="$serveHomeSector" exact="if $serveHomeAnchor? and $serveHomeAnchor.isclass.sector then $serveHomeAnchor else (if $serveHomeAnchor? and $serveHomeAnchor.sector? then @$serveHomeAnchor.sector else $homeSector)"/>
          <set_value name="$serveHomeMatch" exact="false"/>
          <do_if value="$serveHomeAnchor? and $serveHomeAnchor.isclass.station">
            <do_if value="$entrySellStation? and $entrySellStation.exists and $serveHomeAnchor.exists">
              <do_if value="$entrySellStation == $serveHomeAnchor">
                <set_value name="$serveHomeMatch" exact="true"/>
              </do_if>
              <do_elseif value="$serveHomeAnchor.buildstorage? and $serveHomeAnchor.buildstorage.exists and $entrySellStation == $serveHomeAnchor.buildstorage">
                <set_value name="$serveHomeMatch" exact="true"/>
              </do_elseif>
              <do_elseif value="$entrySellStation.isclass.buildstorage and $entrySellStation.base? and $entrySellStation.base.exists and $entrySellStation.base == $serveHomeAnchor">
                <set_value name="$serveHomeMatch" exact="true"/>
              </do_elseif>
              <do_elseif value="$entrySellStation.hascontext.{$serveHomeAnchor}">
                <set_value name="$serveHomeMatch" exact="true"/>
              </do_elseif>
              <do_elseif value="$serveHomeAnchor.hascontext.{$entrySellStation}">
                <set_value name="$serveHomeMatch" exact="true"/>
              </do_elseif>
            </do_if>
            <do_if value="not $serveHomeMatch">
              <continue/>
            </do_if>
          </do_if>
          <do_elseif value="$serveHomeSector? and $serveHomeSector.exists">
            <do_if value="not $entrySellStation? or not $entrySellStation.sector? or @$entrySellStation.sector != $serveHomeSector">
              <continue/>
            </do_if>
          </do_elseif>
        </do_if>
        <!-- MK4 build-storage-only mode: BS buyers within jumpDistanceCoverage; no BS supplier legs. -->
        <do_if value="$mk4BuildStorageOnlyMode and not $entry.$IsSellOnly?">
          <do_if value="$entryBuyStation? and @$entryBuyStation.isclass.buildstorage">
            <continue/>
          </do_if>
          <do_if value="not $entrySellStation? or not @$entrySellStation.isclass.buildstorage">
            <continue/>
          </do_if>
          <!-- BS-only delivery scope: player build storage within jumpDistanceCoverage from home. -->
          <set_value name="$mk4BsoCoverageMax" exact="if $maxDistanceSell? and $maxDistanceSell gt 0 then $maxDistanceSell else $maxDistance"/>
          <set_value name="$mk4BsoInScope" exact="false"/>
          <set_value name="$mk4BsoDist" exact="if $homeSector? and $entrySellStation? and $entrySellStation.sector? then $homeSector.gatedistance.{$entrySellStation.sector} else -1"/>
          <do_if value="$mk4BsoDist ge 0 and ($mk4BsoCoverageMax le 0 or $mk4BsoDist le $mk4BsoCoverageMax)">
            <set_value name="$mk4BsoInScope" exact="true"/>
          </do_if>
          <do_if value="not $mk4BsoInScope">
            <continue/>
          </do_if>
        </do_if>
        <!-- MK4 ware-type policy filter (cache-phase parity with match-phase). -->
        <do_if value="not $entry.$IsSellOnly? and $entrySellStation? and (not $entrySellStation.isclass.buildstorage or $ignoreBuildStorage)">
          <set_value name="$entryTypeWare" exact="if $entry.$Ware? then $entry.$Ware else null"/>
          <do_if value="$entryTypeWare == null and $entry.$BuyOffer? and @$entry.$BuyOffer.exists and @$entry.$BuyOffer.ware != null">
            <set_value name="$entryTypeWare" exact="@$entry.$BuyOffer.ware"/>
          </do_if>
          <do_if value="$entryTypeWare == null and $entry.$SellOffer? and @$entry.$SellOffer.exists and @$entry.$SellOffer.ware != null">
            <set_value name="$entryTypeWare" exact="@$entry.$SellOffer.ware"/>
          </do_if>
          <do_if value="$entryTypeWare?">
            <set_value name="$mk4IsTradeWare" exact="$entrySellStation.tradewares.{$entryTypeWare}.exists"/>
            <set_value name="$mk4IsResource" exact="$entrySellStation.resources.{$entryTypeWare}.exists"/>
            <set_value name="$mk4IsProduct" exact="$entrySellStation.products.{$entryTypeWare}.exists"/>
            <set_value name="$mk4IsIntermediate" exact="false"/>
            <do_if value="$entrySellStation.resources.{$entryTypeWare}.exists and @$entrySellStation.resources.{$entryTypeWare}.intermediate">
              <set_value name="$mk4IsIntermediate" exact="true"/>
            </do_if>
            <do_if value="$entrySellStation.products.{$entryTypeWare}.exists and @$entrySellStation.products.{$entryTypeWare}.intermediate">
              <set_value name="$mk4IsIntermediate" exact="true"/>
            </do_if>
            <set_value name="$mk4IsPureResource" exact="$mk4IsResource and not $mk4IsIntermediate"/>
            <set_value name="$mk4IsIntermediateOrProduct" exact="$mk4IsIntermediate or $mk4IsProduct"/>
            <set_value name="$mk4HasKnownType" exact="$mk4IsTradeWare or $mk4IsResource or $mk4IsProduct"/>
            <set_value name="$mk4AllowedByType" exact="false"/>
            <do_if value="$mk4IsTradeWare and $mk4AllowTradewares">
              <set_value name="$mk4AllowedByType" exact="true"/>
            </do_if>
            <do_if value="not $mk4AllowedByType and $mk4IsPureResource and $mk4AllowResources">
              <set_value name="$mk4AllowedByType" exact="true"/>
            </do_if>
            <do_if value="not $mk4AllowedByType and $mk4IsIntermediateOrProduct and $mk4AllowIntermediates">
              <set_value name="$mk4AllowedByType" exact="true"/>
            </do_if>
            <do_if value="$mk4HasKnownType and not $mk4AllowedByType">
              <continue/>
            </do_if>
          </do_if>
        </do_if>

        <!-- Distance check with per-leg limits (sector-to-sector; station refs break gatedistance). -->
        <do_if value="$maxDistanceBuyLeg gt 0 and $entryBuyStation?">
          <set_value name="$distBuy" exact="-1"/>
          <do_if value="$entryBuyStation.sector? and $entryBuyStation.sector == $homeSector">
            <set_value name="$distBuy" exact="0"/>
          </do_if>
          <do_elseif value="$entryBuyStation.sector?">
            <set_value name="$distBuy" exact="$homeSector.gatedistance.{$entryBuyStation.sector}"/>
          </do_elseif>
          <do_if value="$distBuy lt 0 or $distBuy gt $maxDistanceBuyLeg">
            <continue/>
          </do_if>
        </do_if>
        <do_if value="$maxDistanceSellLeg gt 0 and $entrySellStation?">
          <set_value name="$distSell" exact="-1"/>
          <do_if value="$entrySellStation.sector? and $entrySellStation.sector == $homeSector">
            <set_value name="$distSell" exact="0"/>
          </do_if>
          <do_elseif value="$entrySellStation.sector?">
            <set_value name="$distSell" exact="$homeSector.gatedistance.{$entrySellStation.sector}"/>
          </do_elseif>
          <do_if value="$distSell lt 0 or $distSell gt $maxDistanceSellLeg">
            <continue/>
          </do_if>
        </do_if>

        <!-- ROI / absolute profit check (sell-mode trades only) -->
        <do_if value="not $entry.$IsSellOnly?">
          <do_if value="$minAbsoluteProfit gt 0 and $entry.$Profit? and $entry.$Profit lt $minAbsoluteProfit">
            <continue/>
          </do_if>
          <do_if value="$minROI gt 0 and $entry.$BuyPrice? and $entry.$BuyPrice gt 0">
            <set_value name="$entryROI" exact="($entry.$UnitProfit * 100) / $entry.$BuyPrice"/>
            <do_if value="$entryROI lt $minROI">
              <continue/>
            </do_if>
          </do_if>
        </do_if>

        <!-- Cache Dropoff Tolerance: reject if profit dropped too much since caching -->
        <do_if value="$cacheDropoffTolerance gt 0 and not $entry.$IsSellOnly? and $entry.$UnitProfit? and $entry.$UnitProfit gt 0 and $entry.$BuyOffer? and $entry.$SellOffer?">
          <!-- Only check if both offers still exist (otherwise station-existence check will catch it) -->
          <do_if value="@$entry.$BuyOffer.exists and @$entry.$SellOffer.exists">
            <set_value name="$currentBuyPrice" exact="@$entry.$BuyOffer.unitprice"/>
            <set_value name="$currentSellPrice" exact="@$entry.$SellOffer.unitprice"/>
            <do_if value="$currentBuyPrice? and $currentSellPrice? and $currentBuyPrice gt 0">
              <set_value name="$currentUnitProfit" exact="$currentSellPrice - $currentBuyPrice"/>
              <!-- Calculate how much profit has dropped as % of original -->
              <do_if value="$currentUnitProfit le 0">
                <!-- Profit went negative — always reject -->
                <continue/>
              </do_if>
              <set_value name="$profitDropPct" exact="(($entry.$UnitProfit - $currentUnitProfit) * 100) / $entry.$UnitProfit"/>
              <do_if value="$profitDropPct gt $cacheDropoffTolerance">
                <continue/>
              </do_if>
            </do_if>
          </do_if>
        </do_if>

        <!-- Average-price band filter: quantityfactor vs ware.averageprice (per-ship; drift since cache write). -->
        <do_if value="$bandPriceCheckActive? and $bandPriceCheckActive">
          <set_value name="$isSellOnlyFilter" exact="$entry.$IsSellOnly? and $entry.$IsSellOnly"/>
          <set_value name="$skipSupplierBandFilter" exact="false"/>
          <do_if value="$entry.$PlayerFreeSupplier? and $entry.$PlayerFreeSupplier">
            <set_value name="$skipSupplierBandFilter" exact="true"/>
          </do_if>
          <do_if value="not $skipSupplierBandFilter and $bypassPlayerSellerPricing? and $bypassPlayerSellerPricing and $entry.$BuyOffer? and @$entry.$BuyOffer.exists and @$entry.$BuyOffer.owner.isplayerowned">
            <set_value name="$skipSupplierBandFilter" exact="true"/>
          </do_if>
          <set_value name="$filterCustomerQty" exact="null"/>
          <set_value name="$filterSupplierQty" exact="null"/>
          <do_if value="$entry.$SellOffer? and @$entry.$SellOffer.exists">
            <do_if value="$entry.$SellOffer.quantityfactor?">
              <set_value name="$filterCustomerQty" exact="@$entry.$SellOffer.quantityfactor"/>
            </do_if>
            <do_elseif value="$entry.$SellOffer.unitprice? and $entry.$SellOffer.ware? and @$entry.$SellOffer.ware.averageprice gt 0">
              <set_value name="$filterCustomerQty" exact="@$entry.$SellOffer.unitprice / (@$entry.$SellOffer.ware.averageprice * 100)"/>
            </do_elseif>
            <do_else>
              <continue/>
            </do_else>
            <do_if value="$filterCustomerQty? and $filterCustomerQty lt $bandCustomerQtyMin">
              <continue/>
            </do_if>
          </do_if>
          <do_else>
            <continue/>
          </do_else>
          <do_if value="not $isSellOnlyFilter and not $skipSupplierBandFilter">
            <do_if value="$entry.$BuyOffer? and @$entry.$BuyOffer.exists">
              <do_if value="$entry.$BuyOffer.quantityfactor?">
                <set_value name="$filterSupplierQty" exact="@$entry.$BuyOffer.quantityfactor"/>
              </do_if>
              <do_elseif value="$entry.$BuyOffer.unitprice? and $entry.$BuyOffer.ware? and @$entry.$BuyOffer.ware.averageprice gt 0">
                <set_value name="$filterSupplierQty" exact="@$entry.$BuyOffer.unitprice / (@$entry.$BuyOffer.ware.averageprice * 100)"/>
              </do_elseif>
              <do_else>
                <continue/>
              </do_else>
              <do_if value="$filterSupplierQty? and $filterSupplierQty gt $bandSupplierQtyMax">
                <continue/>
              </do_if>
            </do_if>
            <do_else>
              <continue/>
            </do_else>
            <do_if value="$filterCustomerQty? and $filterSupplierQty?">
              <do_if value="($filterCustomerQty - $filterSupplierQty) lt $bandMinQtySpread">
                <continue/>
              </do_if>
            </do_if>
          </do_if>
        </do_if>

        <!-- Build storage exclusion -->
        <do_if value="$ignoreBuildStorage">
          <do_if value="($entryBuyStation? and @$entryBuyStation.isclass.buildstorage) or ($entrySellStation? and @$entrySellStation.isclass.buildstorage)">
            <continue/>
          </do_if>
        </do_if>

        <!-- Carrier / auxiliary exclusion (stations are never carriers/auxiliaries, only ships can be) -->
        <do_if value="$ignoreCarrierAux">
          <do_if value="($entryBuyStation? and @$entryBuyStation.isclass.ship and (@$entryBuyStation.type == shiptype.carrier or @$entryBuyStation.type == shiptype.resupplier)) or ($entrySellStation? and @$entrySellStation.isclass.ship and (@$entrySellStation.type == shiptype.carrier or @$entrySellStation.type == shiptype.resupplier))">
            <continue/>
          </do_if>
        </do_if>

        <!-- Offer amount pre-filter (CHEAP: universal amount check; do NOT gate on .available alone).
             Build-storage delivery buy-offers often keep .available=false while cargo deficit exists. -->
        <do_if value="not $entry.$IsSellOnly?">
          <do_if value="$entry.$BuyOffer? and @$entry.$BuyOffer.exists">
            <set_value name="$preBuyAmtQuick" exact="@$entry.$BuyOffer.amount"/>
            <do_if value="not $preBuyAmtQuick? or $preBuyAmtQuick le 0">
              <set_value name="$preBuyAmtQuick" exact="0"/>
              <do_if value="$entryBuyStation? and @$entryBuyStation.exists">
                <set_value name="$preBuyWareQuick" exact="if $entry.$Ware? then $entry.$Ware else null"/>
                <do_if value="not $preBuyWareQuick? and @$entry.$BuyOffer.ware != null">
                  <set_value name="$preBuyWareQuick" exact="@$entry.$BuyOffer.ware"/>
                </do_if>
                <do_if value="$preBuyWareQuick?">
                  <get_ware_reservation object="$entryBuyStation" ware="$preBuyWareQuick" type="buy" virtual="false" result="$preBuyResQuick"/>
                  <set_value name="$preBuyAmtQuick" exact="[$entryBuyStation.cargo.{$preBuyWareQuick}.count - $preBuyResQuick, 0].max"/>
                </do_if>
              </do_if>
            </do_if>
            <do_if value="not $preBuyAmtQuick? or $preBuyAmtQuick le 0">
              <continue/>
            </do_if>
          </do_if>
        </do_if>
        <do_if value="$entry.$SellOffer? and @$entry.$SellOffer.exists">
          <do_if value="@$entry.$SellOffer.amount le 0">
            <set_value name="$sellOfferDemandFallback" exact="0"/>
            <do_if value="$entrySellStation? and @$entrySellStation.exists">
              <set_value name="$sellOfferDemandWare" exact="if $entry.$Ware? then $entry.$Ware else null"/>
              <do_if value="not $sellOfferDemandWare? and @$entry.$SellOffer.ware != null">
                <set_value name="$sellOfferDemandWare" exact="@$entry.$SellOffer.ware"/>
              </do_if>
              <do_if value="$sellOfferDemandWare?">
                <set_value name="$sellOfferDemandFallback" exact="[0, $entrySellStation.cargo.{$sellOfferDemandWare}.target - $entrySellStation.cargo.{$sellOfferDemandWare}.count].max"/>
              </do_if>
            </do_if>
            <do_if value="$sellOfferDemandFallback le 0">
              <continue/>
            </do_if>
          </do_if>
        </do_if>

        <!-- Offer capacity check (EXPENSIVE: per-ship, considers pending trade reservations).
             Skip entries where offeramount.{ship} is 0 — station capacity is fully reserved
             by other ships' pending trades. Without this check, the scanner would return 50
             entries all pointing to saturated stations while valid entries deeper in the cache
             go unseen. Per-ware quota below restores diversification without skipping saturated entries entirely. -->
        <do_if value="not $entry.$IsSellOnly?">
          <do_if value="$entry.$BuyOffer? and @$entry.$BuyOffer.exists">
            <set_value name="$preCheckBuyAmt" exact="@$entry.$BuyOffer.offeramount.{$ship}"/>
            <do_if value="(not $preCheckBuyAmt? or $preCheckBuyAmt le 0) and @$entry.$BuyOffer.amount gt 0">
              <set_value name="$preCheckBuyAmt" exact="@$entry.$BuyOffer.amount"/>
            </do_if>
            <!-- Target-count demand fallback (mirrors lib.gt.tradematch + gt_context_diagnose). -->
            <do_if value="(not $preCheckBuyAmt? or $preCheckBuyAmt le 0) and $entrySellStation? and $entrySellStation.exists">
              <set_value name="$preCheckBuyWare" exact="if $entry.$Ware? then $entry.$Ware else null"/>
              <do_if value="not $preCheckBuyWare? and @$entry.$BuyOffer.ware != null">
                <set_value name="$preCheckBuyWare" exact="@$entry.$BuyOffer.ware"/>
              </do_if>
              <do_if value="$preCheckBuyWare?">
                <set_value name="$preCheckBuyAmt" exact="[0, $entrySellStation.cargo.{$preCheckBuyWare}.target - $entrySellStation.cargo.{$preCheckBuyWare}.count].max"/>
              </do_if>
            </do_if>
            <do_if value="not $preCheckBuyAmt? or $preCheckBuyAmt le 0">
              <continue/>
            </do_if>
          </do_if>
        </do_if>
        <do_if value="$entry.$SellOffer? and @$entry.$SellOffer.exists">
          <set_value name="$preCheckSellAmt" exact="@$entry.$SellOffer.offeramount.{$ship}"/>
          <do_if value="(not $preCheckSellAmt? or $preCheckSellAmt le 0) and @$entry.$SellOffer.amount gt 0">
            <set_value name="$preCheckSellAmt" exact="@$entry.$SellOffer.amount"/>
          </do_if>
          <!-- Target-count demand fallback (mirrors lib.gt.tradematch + gt_context_diagnose). -->
          <do_if value="(not $preCheckSellAmt? or $preCheckSellAmt le 0) and $entrySellStation? and $entrySellStation.exists">
            <set_value name="$preCheckSellWare" exact="if $entry.$Ware? then $entry.$Ware else null"/>
            <do_if value="not $preCheckSellWare? and @$entry.$SellOffer.ware != null">
              <set_value name="$preCheckSellWare" exact="@$entry.$SellOffer.ware"/>
            </do_if>
            <do_if value="$preCheckSellWare?">
              <set_value name="$preCheckSellAmt" exact="[0, $entrySellStation.cargo.{$preCheckSellWare}.target - $entrySellStation.cargo.{$preCheckSellWare}.count].max"/>
            </do_if>
          </do_if>
          <do_if value="not $preCheckSellAmt? or $preCheckSellAmt le 0">
            <continue/>
          </do_if>
        </do_if>

        <!-- Hard minimum cargo utilization pre-filter (cache path only, excluded in isolated mode).
             Uses available reserved-aware offer amounts to estimate max feasible load. -->
        <do_if value="$enableMinCargoUtil and not $isIsolatedMode and not $entry.$IsSellOnly?">
          <set_value name="$minUtilVolumePerUnit" exact="1"/>
          <do_if value="$entry.$Ware? and $entry.$Ware.volume?">
            <set_value name="$minUtilVolumePerUnit" exact="$entry.$Ware.volume"/>
          </do_if>
          <set_value name="$minUtilAmountLimit" exact="$preCheckSellAmt"/>
          <do_if value="$preCheckBuyAmt? and $preCheckBuyAmt lt $minUtilAmountLimit">
            <set_value name="$minUtilAmountLimit" exact="$preCheckBuyAmt"/>
          </do_if>
          <set_value name="$minUtilTradeVolume" exact="$minUtilAmountLimit * $minUtilVolumePerUnit"/>
          <set_value name="$minUtilRequiredVolume" exact="($ship.cargo.capacity.all * $cargoUtilThresholdPct) / 100.0"/>
          <do_if value="$minUtilTradeVolume lt $minUtilRequiredVolume">
            <continue/>
          </do_if>
        </do_if>

        <!-- Reservation check: skip trades reserved by other ships (same rule as MD reservations).
             Uses SellOffer object as key (Method B from GT_GenerateTradeKey — most reliable, offer.id often unavailable). -->
        <do_if value="global.$GT_Reservations? and $entry.$SellOffer?">
          <set_value name="$resKey" exact="$entry.$SellOffer"/>
          <do_if value="global.$GT_Reservations.{$resKey}?">
            <set_value name="$resData" exact="global.$GT_Reservations.{$resKey}"/>
            <!-- Only skip if reservation is unexpired AND belongs to a different ship -->
            <do_if value="$resData.$Until? and player.age lt @$resData.$Until and $resData.$Ship? and @$resData.$Ship != $ship">
              <continue/>
            </do_if>
          </do_if>
        </do_if>

        <!-- Per-ware quota gate (after all filters — only count shippable candidates). -->
        <set_value name="$quotaWare" exact="if $entry.$Ware? then $entry.$Ware else null"/>
        <do_if value="not $quotaWare? and $entry.$BuyOffer? and @$entry.$BuyOffer.exists and @$entry.$BuyOffer.ware != null">
          <set_value name="$quotaWare" exact="@$entry.$BuyOffer.ware"/>
        </do_if>
        <do_if value="not $quotaWare? and $entry.$SellOffer? and @$entry.$SellOffer.exists and @$entry.$SellOffer.ware != null">
          <set_value name="$quotaWare" exact="@$entry.$SellOffer.ware"/>
        </do_if>
        <do_if value="$quotaWare?">
          <set_value name="$quotaWareFoundCount" exact="if $foundPerWare.{$quotaWare}? then $foundPerWare.{$quotaWare} else 0"/>
          <do_if value="$quotaWareFoundCount ge $perWareCap">
            <continue/>
          </do_if>
        </do_if>

        <!-- Trade rules + live profit gate (validation parity): run after offer-amount checks on live refs. -->
        <do_if value="not $entry.$IsSellOnly?">
          <set_value name="$trRuleBuyStation" exact="null"/>
          <do_if value="$entry.$BuyStation? and @$entry.$BuyStation.exists">
            <set_value name="$trRuleBuyStation" exact="$entry.$BuyStation"/>
          </do_if>
          <do_elseif value="$entry.$BuyOffer? and @$entry.$BuyOffer.exists and $entry.$BuyOffer.owner? and @$entry.$BuyOffer.owner.exists">
            <set_value name="$trRuleBuyStation" exact="@$entry.$BuyOffer.owner"/>
          </do_elseif>
          <set_value name="$trRuleSellStation" exact="null"/>
          <do_if value="$entry.$SellStation? and @$entry.$SellStation.exists">
            <set_value name="$trRuleSellStation" exact="$entry.$SellStation"/>
          </do_if>
          <do_elseif value="$entry.$SellOffer? and @$entry.$SellOffer.exists and $entry.$SellOffer.owner? and @$entry.$SellOffer.owner.exists">
            <set_value name="$trRuleSellStation" exact="@$entry.$SellOffer.owner"/>
          </do_elseif>
          <do_if value="not $ignoreTradeRules">
            <!-- Trade rules are a player-station feature only; NPC×NPC cantradewith is not enforced. -->
            <set_value name="$trPlayerStationInvolved" exact="false"/>
            <do_if value="$trRuleBuyStation? and @$trRuleBuyStation.exists">
              <do_if value="@$trRuleBuyStation.isplayerowned">
                <set_value name="$trPlayerStationInvolved" exact="true"/>
              </do_if>
              <do_elseif value="@$trRuleBuyStation.isclass.buildstorage and $trRuleBuyStation.base? and @$trRuleBuyStation.base.exists and @$trRuleBuyStation.base.isplayerowned">
                <set_value name="$trPlayerStationInvolved" exact="true"/>
              </do_elseif>
            </do_if>
            <do_if value="not $trPlayerStationInvolved and $trRuleSellStation? and @$trRuleSellStation.exists">
              <do_if value="@$trRuleSellStation.isplayerowned">
                <set_value name="$trPlayerStationInvolved" exact="true"/>
              </do_if>
              <do_elseif value="@$trRuleSellStation.isclass.buildstorage and $trRuleSellStation.base? and @$trRuleSellStation.base.exists and @$trRuleSellStation.base.isplayerowned">
                <set_value name="$trPlayerStationInvolved" exact="true"/>
              </do_elseif>
            </do_if>
            <do_if value="$trPlayerStationInvolved">
              <do_if value="$entry.$SellOffer? and @$entry.$SellOffer.exists and $trRuleBuyStation? and @$trRuleBuyStation.exists and not $entry.$SellOffer.cantradewith.{$trRuleBuyStation}">
                <continue/>
              </do_if>
              <do_if value="$entry.$BuyOffer? and @$entry.$BuyOffer.exists and $trRuleSellStation? and @$trRuleSellStation.exists and not $entry.$BuyOffer.cantradewith.{$trRuleSellStation}">
                <continue/>
              </do_if>
            </do_if>
          </do_if>
          <do_if value="$entry.$BuyOffer? and @$entry.$BuyOffer.exists and $entry.$SellOffer? and @$entry.$SellOffer.exists">
            <do_if value="$entry.$BuyOffer.unitprice? and $entry.$SellOffer.unitprice? and ($entry.$SellOffer.unitprice - $entry.$BuyOffer.unitprice) le 0">
              <continue/>
            </do_if>
          </do_if>
        </do_if>

        <!-- Entry passed all filters -->
        <append_to_list name="$tradeList" exact="$entry"/>
        <set_value name="$foundCount" operation="add"/>
        <do_if value="$quotaWare?">
          <set_value name="$foundPerWare.{$quotaWare}" exact="if $foundPerWare.{$quotaWare}? then ($foundPerWare.{$quotaWare} + 1) else 1"/>
        </do_if>
        <do_if value="$entry.$Score gt $bestScore">
          <set_value name="$bestScore" exact="$entry.$Score"/>
          <set_value name="$bestTrade" exact="$entry"/>
        </do_if>
        <!-- Stop once we have enough valid trades -->
        <do_if value="$foundCount ge $maxEntries">
          <break/>
        </do_if>
        <do_if value="($visitIdx % 10) == 0">
          <wait exact="this.$gt_yieldMs * 1ms" comment="Yield cache scan loop"/>
        </do_if>
      </do_all>

      <!-- When no trades matched, purge entries whose offers are globally exhausted (not transient per-ship reservation).
           Keeps pool count honest so scheduler escalates to live instead of parking on zombie rows. -->
      <set_value name="$purgedDeadCount" exact="0"/>
      <do_if value="$foundCount == 0 and $homeCache? and $homeCache.count gt 0">
        <set_value name="$deadScanCount" exact="@$homeCache.count"/>
        <do_all exact="$deadScanCount" counter="$ddi" reverse="true">
          <do_if value="$ddi gt $homeCache.count">
            <continue/>
          </do_if>
          <set_value name="$deadEntry" exact="@$homeCache.{$ddi}"/>
          <do_if value="not $deadEntry?">
            <continue/>
          </do_if>
          <set_value name="$deadRemove" exact="false"/>
          <set_value name="$deadSellStation" exact="null"/>
          <do_if value="$deadEntry.$SellStation? and @$deadEntry.$SellStation.exists">
            <set_value name="$deadSellStation" exact="$deadEntry.$SellStation"/>
          </do_if>
          <do_elseif value="$deadEntry.$SellOffer? and @$deadEntry.$SellOffer.exists and $deadEntry.$SellOffer.buyer? and @$deadEntry.$SellOffer.buyer.exists">
            <set_value name="$deadSellStation" exact="@$deadEntry.$SellOffer.buyer"/>
          </do_elseif>
          <do_if value="$deadEntry.$SellOffer? and @$deadEntry.$SellOffer.exists">
            <set_value name="$deadSellAmt" exact="@$deadEntry.$SellOffer.amount"/>
            <do_if value="not $deadSellAmt? or $deadSellAmt le 0">
              <set_value name="$deadSellDemand" exact="0"/>
              <do_if value="$deadSellStation? and @$deadSellStation.exists">
                <set_value name="$deadSellWare" exact="if $deadEntry.$Ware? then $deadEntry.$Ware else null"/>
                <do_if value="not $deadSellWare? and @$deadEntry.$SellOffer.ware != null">
                  <set_value name="$deadSellWare" exact="@$deadEntry.$SellOffer.ware"/>
                </do_if>
                <do_if value="$deadSellWare?">
                  <set_value name="$deadSellDemand" exact="[0, $deadSellStation.cargo.{$deadSellWare}.target - $deadSellStation.cargo.{$deadSellWare}.count].max"/>
                </do_if>
              </do_if>
              <do_if value="$deadSellDemand le 0">
                <set_value name="$deadRemove" exact="true"/>
              </do_if>
            </do_if>
          </do_if>
          <do_if value="not $deadRemove and not $deadEntry.$IsSellOnly? and $deadEntry.$BuyOffer? and @$deadEntry.$BuyOffer.exists">
            <set_value name="$deadBuyAmt" exact="@$deadEntry.$BuyOffer.amount"/>
            <do_if value="not $deadBuyAmt? or $deadBuyAmt le 0">
              <set_value name="$deadBuySupply" exact="0"/>
              <set_value name="$deadBuyStation" exact="null"/>
              <do_if value="$deadEntry.$BuyStation? and @$deadEntry.$BuyStation.exists">
                <set_value name="$deadBuyStation" exact="$deadEntry.$BuyStation"/>
              </do_if>
              <do_elseif value="$deadEntry.$BuyOffer.seller? and @$deadEntry.$BuyOffer.seller.exists">
                <set_value name="$deadBuyStation" exact="@$deadEntry.$BuyOffer.seller"/>
              </do_elseif>
              <do_if value="$deadBuyStation? and @$deadBuyStation.exists">
                <set_value name="$deadBuyWare" exact="if $deadEntry.$Ware? then $deadEntry.$Ware else null"/>
                <do_if value="not $deadBuyWare? and @$deadEntry.$BuyOffer.ware != null">
                  <set_value name="$deadBuyWare" exact="@$deadEntry.$BuyOffer.ware"/>
                </do_if>
                <do_if value="$deadBuyWare?">
                  <get_ware_reservation object="$deadBuyStation" ware="$deadBuyWare" type="buy" virtual="false" result="$deadBuyRes"/>
                  <set_value name="$deadBuySupply" exact="[$deadBuyStation.cargo.{$deadBuyWare}.count - $deadBuyRes, 0].max"/>
                </do_if>
              </do_if>
              <do_if value="$deadBuySupply le 0">
                <set_value name="$deadRemove" exact="true"/>
              </do_if>
            </do_if>
          </do_if>
          <!-- Unreadable for any ship with this fleet config: price band drift or cargo-util floor (diag omits these). -->
          <do_if value="not $deadRemove and $bandPriceCheckActive? and $bandPriceCheckActive and not ($deadEntry.$IsSellOnly? and $deadEntry.$IsSellOnly)">
            <set_value name="$deadSkipSupplierBand" exact="false"/>
            <do_if value="$deadEntry.$PlayerFreeSupplier? and $deadEntry.$PlayerFreeSupplier">
              <set_value name="$deadSkipSupplierBand" exact="true"/>
            </do_if>
            <do_if value="not $deadSkipSupplierBand and $bypassPlayerSellerPricing? and $bypassPlayerSellerPricing and $deadEntry.$BuyOffer? and @$deadEntry.$BuyOffer.exists and @$deadEntry.$BuyOffer.owner.isplayerowned">
              <set_value name="$deadSkipSupplierBand" exact="true"/>
            </do_if>
            <do_if value="$deadEntry.$SellOffer? and @$deadEntry.$SellOffer.exists">
              <set_value name="$deadCustQty" exact="null"/>
              <do_if value="$deadEntry.$SellOffer.quantityfactor?">
                <set_value name="$deadCustQty" exact="@$deadEntry.$SellOffer.quantityfactor"/>
              </do_if>
              <do_elseif value="$deadEntry.$SellOffer.unitprice? and $deadEntry.$SellOffer.ware? and @$deadEntry.$SellOffer.ware.averageprice gt 0">
                <set_value name="$deadCustQty" exact="@$deadEntry.$SellOffer.unitprice / (@$deadEntry.$SellOffer.ware.averageprice * 100)"/>
              </do_elseif>
              <do_else>
                <set_value name="$deadRemove" exact="true"/>
              </do_else>
              <do_if value="not $deadRemove and $deadCustQty? and $deadCustQty lt $bandCustomerQtyMin">
                <set_value name="$deadRemove" exact="true"/>
              </do_if>
              <do_if value="not $deadRemove and not $deadSkipSupplierBand and $deadEntry.$BuyOffer? and @$deadEntry.$BuyOffer.exists">
                <set_value name="$deadSupQty" exact="null"/>
                <do_if value="$deadEntry.$BuyOffer.quantityfactor?">
                  <set_value name="$deadSupQty" exact="@$deadEntry.$BuyOffer.quantityfactor"/>
                </do_if>
                <do_elseif value="$deadEntry.$BuyOffer.unitprice? and $deadEntry.$BuyOffer.ware? and @$deadEntry.$BuyOffer.ware.averageprice gt 0">
                  <set_value name="$deadSupQty" exact="@$deadEntry.$BuyOffer.unitprice / (@$deadEntry.$BuyOffer.ware.averageprice * 100)"/>
                </do_elseif>
                <do_else>
                  <set_value name="$deadRemove" exact="true"/>
                </do_else>
                <do_if value="not $deadRemove and $deadSupQty? and $deadSupQty gt $bandSupplierQtyMax">
                  <set_value name="$deadRemove" exact="true"/>
                </do_if>
                <do_if value="not $deadRemove and $deadCustQty? and $deadSupQty? and ($deadCustQty - $deadSupQty) lt $bandMinQtySpread">
                  <set_value name="$deadRemove" exact="true"/>
                </do_if>
              </do_if>
            </do_if>
            <do_elseif value="not ($deadEntry.$IsSellOnly? and $deadEntry.$IsSellOnly)">
              <set_value name="$deadRemove" exact="true"/>
            </do_elseif>
          </do_if>
          <do_if value="not $deadRemove and $enableMinCargoUtil and not $isIsolatedMode and not ($deadEntry.$IsSellOnly? and $deadEntry.$IsSellOnly)">
            <set_value name="$deadMinSellAmt" exact="0"/>
            <set_value name="$deadMinBuyAmt" exact="0"/>
            <do_if value="$deadEntry.$SellOffer? and @$deadEntry.$SellOffer.exists">
              <set_value name="$deadMinSellAmt" exact="@$deadEntry.$SellOffer.offeramount.{$ship}"/>
              <do_if value="(not $deadMinSellAmt? or $deadMinSellAmt le 0) and @$deadEntry.$SellOffer.amount gt 0">
                <set_value name="$deadMinSellAmt" exact="@$deadEntry.$SellOffer.amount"/>
              </do_if>
            </do_if>
            <do_if value="$deadEntry.$BuyOffer? and @$deadEntry.$BuyOffer.exists">
              <set_value name="$deadMinBuyAmt" exact="@$deadEntry.$BuyOffer.offeramount.{$ship}"/>
              <do_if value="(not $deadMinBuyAmt? or $deadMinBuyAmt le 0) and @$deadEntry.$BuyOffer.amount gt 0">
                <set_value name="$deadMinBuyAmt" exact="@$deadEntry.$BuyOffer.amount"/>
              </do_if>
            </do_if>
            <set_value name="$deadMinVolPerUnit" exact="1"/>
            <do_if value="$deadEntry.$Ware? and $deadEntry.$Ware.volume?">
              <set_value name="$deadMinVolPerUnit" exact="$deadEntry.$Ware.volume"/>
            </do_if>
            <set_value name="$deadMinAmtLimit" exact="$deadMinSellAmt"/>
            <do_if value="$deadMinBuyAmt? and $deadMinBuyAmt lt $deadMinAmtLimit">
              <set_value name="$deadMinAmtLimit" exact="$deadMinBuyAmt"/>
            </do_if>
            <set_value name="$deadMinTradeVol" exact="$deadMinAmtLimit * $deadMinVolPerUnit"/>
            <set_value name="$deadMinRequiredVol" exact="($ship.cargo.capacity.all * $cargoUtilThresholdPct) / 100.0"/>
            <do_if value="$deadMinTradeVol lt $deadMinRequiredVol">
              <set_value name="$deadRemove" exact="true"/>
            </do_if>
          </do_if>
          <do_if value="$deadRemove">
            <do_if value="this.$gt_cachePoolIsMk4">
              <remove_value name="global.$GT_TradeCacheMK4.{$cacheHomeKey}.{$ddi}"/>
            </do_if>
            <do_else>
              <remove_value name="global.$GT_TradeCache.{$cacheHomeKey}.{$ddi}"/>
            </do_else>
            <set_value name="$purgedDeadCount" operation="add"/>
          </do_if>
        </do_all>
        <do_if value="$purgedDeadCount gt 0">
          <set_value name="$homeCache" exact="null"/>
          <do_if value="this.$gt_cachePoolIsMk4">
            <set_value name="$homeCache" exact="@global.$GT_TradeCacheMK4.{$cacheHomeKey}"/>
          </do_if>
          <do_else>
            <set_value name="$homeCache" exact="@global.$GT_TradeCache.{$cacheHomeKey}"/>
          </do_else>
          <set_value name="$homeCacheCount" exact="0"/>
          <do_if value="$homeCache?">
            <set_value name="$homeCacheCount" exact="@$homeCache.count"/>
          </do_if>
          <do_if value="@global.$GT_GlobalSettings.$Debug.$EnableDebugLogging">
            <debug_text text="'[GT-CacheSearch] ' + $ship.idcode + ': Read-time purge removed ' + $purgedDeadCount + ' unreadable entries from ' + $cacheHomeKey.knownname + ' (remaining: ' + $homeCacheCount + ')'" chance="100"/>
          </do_if>
        </do_if>
      </do_if>

      <return value="table[
        $Found = ($bestTrade != null),
        $BestTrade = $bestTrade,
        $BestScore = $bestScore,
        $TradeList = $tradeList,
        $PurgedStale = $purgedStaleCount,
        $PoolSizeAfter = $homeCacheCount
      ]"/>
    </actions>
  </attention>
</aiscript>
